lidar_processing/__init__.py
lidar_processing/constants.py
lidar_processing/depolarization.py
lidar_processing/elastic_retrievals.py
lidar_processing/error_functions.py
lidar_processing/fit_checks.py
lidar_processing/gluing_damico.py
lidar_processing/helper_functions.py
lidar_processing/hsrl_retrieval.py
lidar_processing/pre_processing.py
lidar_processing/raman_retrievals.py
lidar_processing/tests/__init__.py
lidar_processing/tests/test_depolarization.py
lidar_processing/tests/test_elastic_retrieval.py
lidar_processing/tests/test_fit_checks.py
lidar_processing/tests/test_pre_processing.py
lidar_processing/tests/test_raman_retrievals.py
lidar_processing-0.3.0.dist-info/LICENCE.txt
lidar_processing-0.3.0.dist-info/METADATA
lidar_processing-0.3.0.dist-info/WHEEL
lidar_processing-0.3.0.dist-info/top_level.txt
lidar_processing-0.3.0.dist-info/RECORD
