Metadata-Version: 2.1
Name: lidar-processing
Version: 0.3.0
Summary: Routines for atmospheric lidar processing.
Home-page: https://gitlab.com/ioannis_binietoglou/lidar-processing
Author: Ioannis Binietoglou
Author-email: ioannis@inoe.ro
License: MIT
Keywords: lidar aerosol processing
Platform: UNKNOWN
Classifier: Development Status :: 4 - Beta
Classifier: License :: OSI Approved :: MIT License
Classifier: Programming Language :: Python :: 3
Classifier: Intended Audience :: Science/Research
Classifier: Topic :: Scientific/Engineering :: Atmospheric Science
Requires-Dist: netCDF4
Requires-Dist: numpy
Requires-Dist: matplotlib
Requires-Dist: scipy
Requires-Dist: sphinx
Requires-Dist: numpydoc
Requires-Dist: pyyaml
